{
  "file_id": "HI_158.txt",
  "num_narrative_agents": 3,
  "num_subnarrative_agents": 1,
  "narrative_votes": [
    [
      "URW: Blaming the war on others rather than the invader",
      "URW: Russia is the Victim",
      "URW: Discrediting Ukraine",
      "URW: Speculating war outcomes"
    ],
    [
      "URW: Blaming the war on others rather than the invader",
      "URW: Russia is the Victim",
      "URW: Discrediting Ukraine",
      "URW: Speculating war outcomes",
      "URW: Amplifying war-related fears"
    ],
    [
      "URW: Blaming the war on others rather than the invader",
      "URW: Russia is the Victim",
      "URW: Discrediting Ukraine",
      "URW: Speculating war outcomes"
    ]
  ],
  "narrative_votes_with_evidence": [
    [
      {
        "narrative_name": "URW: Blaming the war on others rather than the invader",
        "evidence_quote": "पुतिन ने कहा कि यूक्रेन देश के दक्षिण में अपनी घुसपैठ के साथ रूसी स्थिरता को कमजोर करने की कोशिश कर रहा है",
        "reasoning": "इस उद्धरण में, पुतिन यूक्रेन पर रूसी स्थिरता को कमजोर करने का आरोप लगा रहे हैं, जो युद्ध के लिए जिम्मेदारी को रूस से यूक्रेन पर स्थानांतरित करने का एक उदाहरण है।"
      },
      {
        "narrative_name": "URW: Russia is the Victim",
        "evidence_quote": "पुतिन ने कहा कि यूक्रेन देश के दक्षिण में अपनी घुसपैठ के साथ रूसी स्थिरता को कमजोर करने की कोशिश कर रहा है",
        "reasoning": "इस उद्धरण में, पुतिन यूक्रेन की कार्रवाई को रूसी स्थिरता के लिए खतरा बता रहे हैं, जो रूस को पीड़ित के रूप में चित्रित करने का एक उदाहरण है।"
      },
      {
        "narrative_name": "URW: Discrediting Ukraine",
        "evidence_quote": "पुतिन ने कहा कि यूक्रेनी सशस्त्र बलों के नुकसान उनके लिए नाटकीय रूप से बढ़ रहे हैं",
        "reasoning": "इस उद्धरण में, पुतिन यूक्रेनी सशस्त्र बलों की क्षमता पर संदेह कर रहे हैं, जो यूक्रेन को कमजोर और अक्षम बताने का एक उदाहरण है।"
      },
      {
        "narrative_name": "URW: Speculating war outcomes",
        "evidence_quote": "लेफ्टिनेंट जनरल इहोर रोमानेंको ने अल जजीरा से कहा कि यूक्रेन के लोगों को एक लंबे युद्ध, एक कठिन युद्ध, एक खूनी युद्ध की संभावना दिखती है",
        "reasoning": "इस उद्धरण में, रोमानेंको युद्ध के संभावित परिणामों के बारे में भविष्यवाणी कर रहे हैं, जो युद्ध के परिणामों पर विचार-विमर्श करने का एक उदाहरण है।"
      }
    ],
    [
      {
        "narrative_name": "URW: Blaming the war on others rather than the invader",
        "evidence_quote": "पुतिन ने कहा कि यूक्रेन देश के दक्षिण में अपनी घुसपैठ के साथ रूसी स्थिरता को कमजोर करने की कोशिश कर रहा है",
        "reasoning": "इस उद्धरण में, पुतिन यूक्रेन पर रूसी स्थिरता को कमजोर करने का आरोप लगा रहे हैं, जो युद्ध के लिए जिम्मेदारी को रूस से यूक्रेन पर स्थानांतरित करने का एक स्पष्ट प्रयास है।"
      },
      {
        "narrative_name": "URW: Russia is the Victim",
        "evidence_quote": "पुतिन ने कहा कि यूक्रेन देश के दक्षिण में अपनी घुसपैठ के साथ रूसी स्थिरता को कमजोर करने की कोशिश कर रहा है",
        "reasoning": "इस उद्धरण में, पुतिन यूक्रेन की कार्रवाई को रूसी स्थिरता के लिए खतरा के रूप में चित्रित कर रहे हैं, जो रूस को पीड़ित के रूप में प्रस्तुत करता है।"
      },
      {
        "narrative_name": "URW: Discrediting Ukraine",
        "evidence_quote": "पुतिन ने कहा कि यूक्रेनी सशस्त्र बलों के नुकसान उनके लिए नाटकीय रूप से बढ़ रहे हैं",
        "reasoning": "इस उद्धरण में, पुतिन यूक्रेनी सेना की क्षमता और स्थिति पर संदेह पैदा कर रहे हैं, जो यूक्रेन की विश्वसनीयता और क्षमता को कम करने का एक प्रयास है।"
      },
      {
        "narrative_name": "URW: Speculating war outcomes",
        "evidence_quote": "लेफ्टिनेंट जनरल इहोर रोमानेंको ने अल जजीरा से कहा कि यूक्रेन के लोगों को एक लंबे युद्ध, एक कठिन युद्ध, एक खूनी युद्ध की संभावना दिखती है",
        "reasoning": "इस उद्धरण में, रोमानेंको युद्ध के संभावित परिणामों के बारे में अनुमान लगा रहे हैं, जो युद्ध के परिणामों के बारे में भविष्यवाणी करने का एक प्रयास है।"
      },
      {
        "narrative_name": "URW: Amplifying war-related fears",
        "evidence_quote": "लेफ्टिनेंट जनरल इहोर रोमानेंको ने अल जजीरा से कहा कि यूक्रेन के लोगों को एक लंबे युद्ध, एक कठिन युद्ध, एक खूनी युद्ध की संभावना दिखती है",
        "reasoning": "इस उद्धरण में, रोमानेंको युद्ध की गंभीरता और इसके संभावित परिणामों के बारे में चिंता पैदा कर रहे हैं, जो युद्ध से संबंधित डर को बढ़ाने का एक प्रयास है।"
      }
    ],
    [
      {
        "narrative_name": "URW: Blaming the war on others rather than the invader",
        "evidence_quote": "पुतिन ने कहा कि यूक्रेन देश के दक्षिण में अपनी घुसपैठ के साथ रूसी स्थिरता को कमजोर करने की कोशिश कर रहा है",
        "reasoning": "इस उद्धरण में, पुतिन यूक्रेन पर रूसी स्थिरता को कमजोर करने का आरोप लगा रहे हैं, जो युद्ध के लिए यूक्रेन को दोषी ठहराने का एक उदाहरण है।"
      },
      {
        "narrative_name": "URW: Russia is the Victim",
        "evidence_quote": "पुतिन ने कहा कि यूक्रेन देश के दक्षिण में अपनी घुसपैठ के साथ रूसी स्थिरता को कमजोर करने की कोशिश कर रहा है",
        "reasoning": "इस उद्धरण में, पुतिन रूस को यूक्रेन की घुसपैठ का शिकार बता रहे हैं, जो रूस को पीड़ित के रूप में चित्रित करने का एक उदाहरण है।"
      },
      {
        "narrative_name": "URW: Discrediting Ukraine",
        "evidence_quote": "पुतिन ने कहा कि यूक्रेनी सशस्त्र बलों के नुकसान उनके लिए नाटकीय रूप से बढ़ रहे हैं",
        "reasoning": "इस उद्धरण में, पुतिन यूक्रेनी सशस्त्र बलों की कमजोरी पर जोर दे रहे हैं, जो यूक्रेन को कमजोर और अक्षम बताने का एक उदाहरण है।"
      },
      {
        "narrative_name": "URW: Speculating war outcomes",
        "evidence_quote": "लेफ्टिनेंट जनरल इहोर रोमानेंको ने अल जजीरा से कहा कि यूक्रेन के लोगों को एक लंबे युद्ध, एक कठिन युद्ध, एक खूनी युद्ध की संभावना दिखती है",
        "reasoning": "इस उद्धरण में, रोमानेंको युद्ध के परिणामों के बारे में अनुमान लगा रहे हैं, जो युद्ध के परिणामों के बारे में भविष्यवाणी करने का एक उदाहरण है।"
      }
    ]
  ],
  "subnarrative_votes_flat": [],
  "subnarrative_votes_flat_with_evidence": [],
  "narrative_aggregation_method": "intersection",
  "subnarrative_aggregation_method": "intersection",
  "aggregated_narratives": [
    "URW: Blaming the war on others rather than the invader",
    "URW: Russia is the Victim",
    "URW: Discrediting Ukraine",
    "URW: Speculating war outcomes"
  ],
  "aggregated_subnarratives": [
    "URW: Blaming the war on others rather than the invader: Ukraine is the aggressor",
    "URW: Blaming the war on others rather than the invader: Other",
    "URW: Russia is the Victim: Russia actions in Ukraine are only self-defence",
    "URW: Russia is the Victim: The West is russophobic",
    "URW: Discrediting Ukraine: Discrediting Ukrainian military",
    "URW: Discrediting Ukraine: Ukraine is a puppet of the West",
    "URW: Speculating war outcomes: Russian army is collapsing",
    "URW: Speculating war outcomes: Ukrainian army is collapsing"
  ],
  "narrative_agent_metadata": [
    {
      "agent_id": 1,
      "status": "success",
      "n_labels": 4
    },
    {
      "agent_id": 2,
      "status": "success",
      "n_labels": 5
    },
    {
      "agent_id": 3,
      "status": "success",
      "n_labels": 4
    }
  ],
  "subnarrative_agent_metadata": [],
  "narrative_fuzzy_matches": [
    {
      "original": "URW: Blaming the war on others rather than the invader",
      "matched": "URW: Blaming the war on others rather than the invader",
      "score": 100.0,
      "type": "exact"
    },
    {
      "original": "URW: Russia is the Victim",
      "matched": "URW: Russia is the Victim",
      "score": 100.0,
      "type": "exact"
    },
    {
      "original": "URW: Discrediting Ukraine",
      "matched": "URW: Discrediting Ukraine",
      "score": 100.0,
      "type": "exact"
    },
    {
      "original": "URW: Speculating war outcomes",
      "matched": "URW: Speculating war outcomes",
      "score": 100.0,
      "type": "exact"
    }
  ],
  "subnarrative_fuzzy_matches": [
    {
      "original": "URW: Blaming the war on others rather than the invader: Ukraine is the aggressor",
      "matched": "URW: Blaming the war on others rather than the invader: Ukraine is the aggressor",
      "score": 100.0,
      "type": "exact"
    },
    {
      "original": "URW: Blaming the war on others rather than the invader: Other",
      "matched": "URW: Blaming the war on others rather than the invader: Other",
      "score": 100.0,
      "type": "exact"
    },
    {
      "original": "URW: Russia is the Victim: Russia actions in Ukraine are only self-defence",
      "matched": "URW: Russia is the Victim: Russia actions in Ukraine are only self-defence",
      "score": 100.0,
      "type": "exact"
    },
    {
      "original": "URW: Russia is the Victim: The West is russophobic",
      "matched": "URW: Russia is the Victim: The West is russophobic",
      "score": 100.0,
      "type": "exact"
    },
    {
      "original": "URW: Discrediting Ukraine: Discrediting Ukrainian military",
      "matched": "URW: Discrediting Ukraine: Discrediting Ukrainian military",
      "score": 100.0,
      "type": "exact"
    },
    {
      "original": "URW: Discrediting Ukraine: Ukraine is a puppet of the West",
      "matched": "URW: Discrediting Ukraine: Ukraine is a puppet of the West",
      "score": 100.0,
      "type": "exact"
    },
    {
      "original": "URW: Speculating war outcomes: Russian army is collapsing",
      "matched": "URW: Speculating war outcomes: Russian army is collapsing",
      "score": 100.0,
      "type": "exact"
    },
    {
      "original": "URW: Speculating war outcomes: Ukrainian army is collapsing",
      "matched": "URW: Speculating war outcomes: Ukrainian army is collapsing",
      "score": 100.0,
      "type": "exact"
    }
  ]
}