{
  "file_id": "HI_159.txt",
  "num_narrative_agents": 3,
  "num_subnarrative_agents": 1,
  "narrative_votes": [
    [
      "URW: Speculating war outcomes",
      "URW: Discrediting the West, Diplomacy",
      "URW: Praise of Russia"
    ],
    [
      "URW: Speculating war outcomes",
      "URW: Discrediting Ukraine",
      "URW: Praise of Russia"
    ],
    [
      "URW: Speculating war outcomes",
      "URW: Discrediting the West, Diplomacy",
      "URW: Praise of Russia"
    ]
  ],
  "narrative_votes_with_evidence": [
    [
      {
        "narrative_name": "URW: Speculating war outcomes",
        "evidence_quote": "रूस और यूक्रेन का युद्ध अब और भी ज्यादा आक्रामक हो गया है दोनों ही पक्षों के लोग लगातार हमलावर हो रहे हैं।",
        "reasoning": "यह उद्धरण युद्ध के परिणामों के बारे में भविष्यवाणी करता है, जो कि 'Speculating war outcomes' श्रेणी के अंतर्गत आता है।"
      },
      {
        "narrative_name": "URW: Discrediting the West, Diplomacy",
        "evidence_quote": "यूक्रेन के हमलों में अपनी जमीन गंवाने के बाद भी रूस ने अपना कड़ा रुख नहीं बदला है।",
        "reasoning": "यह उद्धरण रूस के कठोर रुख को दर्शाता है, जो कि 'Discrediting the West, Diplomacy' श्रेणी के अंतर्गत आता है।"
      },
      {
        "narrative_name": "URW: Praise of Russia",
        "evidence_quote": "रूस की तरफ से दावा किया गया है कि उसने डोनेट्स्क के पूर्वी यूक्रेनी क्षेत्र में एक महत्वपूर्ण लॉजिस्टिक हब के पास एक गांव पर कब्जा कर लिया है।",
        "reasoning": "यह उद्धरण रूस की सैन्य उपलब्धियों को दर्शाता है, जो कि 'Praise of Russia' श्रेणी के अंतर्गत आता है।"
      }
    ],
    [
      {
        "narrative_name": "URW: Speculating war outcomes",
        "evidence_quote": "रूस और यूक्रेन का युद्ध अब और भी ज्यादा आक्रामक हो गया है दोनों ही पक्षों के लोग लगातार हमलावर हो रहे हैं।",
        "reasoning": "यह उद्धरण युद्ध की वर्तमान स्थिति के बारे में एक भविष्यवाणी करता है, जो कि दोनों पक्षों के बीच बढ़ते आक्रामकता को दर्शाता है।"
      },
      {
        "narrative_name": "URW: Discrediting Ukraine",
        "evidence_quote": "हमला करके यूक्रेन ने भले ही रूसी कुर्स्क क्षेत्र में बढ़त हासिल कर रखी हो लेकिन इन हमलों ने रूस का मनोबल तोड़ने की जगह उसे और भी ज्यादा हमलावर बना दिया है।",
        "reasoning": "यह उद्धरण यूक्रेन की सैन्य कार्रवाइयों को नकारात्मक रूप से चित्रित करता है, जो कि रूस को और अधिक आक्रामक बनाने के लिए प्रेरित करता है।"
      },
      {
        "narrative_name": "URW: Praise of Russia",
        "evidence_quote": "रूस की सेना ने लगातार अपने कब्जे वाले क्षेत्रों पर मजबूत पकड़ बनाते हुए यूक्रेन की सेना को पीछे खदेड़ने का काम किया है।",
        "reasoning": "यह उद्धरण रूसी सेना की क्षमता और सफलता को प्रदर्शित करता है, जो कि रूस की सैन्य शक्ति की प्रशंसा को दर्शाता है।"
      }
    ],
    [
      {
        "narrative_name": "URW: Speculating war outcomes",
        "evidence_quote": "रूस और यूक्रेन का युद्ध अब और भी ज्यादा आक्रामक हो गया है दोनों ही पक्षों के लोग लगातार हमलावर हो रहे हैं।",
        "reasoning": "यह उद्धरण युद्ध के परिणामों के बारे में भविष्यवाणी करता है, जो कि 'Speculating war outcomes' की परिभाषा के अनुसार है।"
      },
      {
        "narrative_name": "URW: Discrediting the West, Diplomacy",
        "evidence_quote": "यूक्रेन के हमलों में अपनी जमीन गंवाने के बाद भी रूस ने अपना कड़ा रुख नहीं बदला है।",
        "reasoning": "यह उद्धरण रूस के कठोर रुख को दर्शाता है, जो कि 'Discrediting the West, Diplomacy' की परिभाषा के अनुसार है, जिसमें पश्चिमी देशों की आलोचना की जाती है।"
      },
      {
        "narrative_name": "URW: Praise of Russia",
        "evidence_quote": "रूस की तरफ से दावा किया गया है कि उसने डोनेट्स्क के पूर्वी यूक्रेनी क्षेत्र में एक महत्वपूर्ण लॉजिस्टिक हब के पास एक गांव पर कब्जा कर लिया है।",
        "reasoning": "यह उद्धरण रूस की सैन्य उपलब्धियों को दर्शाता है, जो कि 'Praise of Russia' की परिभाषा के अनुसार है।"
      }
    ]
  ],
  "subnarrative_votes_flat": [],
  "subnarrative_votes_flat_with_evidence": [],
  "narrative_aggregation_method": "intersection",
  "subnarrative_aggregation_method": "intersection",
  "aggregated_narratives": [
    "URW: Speculating war outcomes",
    "URW: Praise of Russia"
  ],
  "aggregated_subnarratives": [
    "URW: Speculating war outcomes: Russian army will lose all the occupied territories",
    "URW: Speculating war outcomes: Other",
    "URW: Praise of Russia: Praise of Russian military might",
    "URW: Praise of Russia: Russia is a guarantor of peace and prosperity"
  ],
  "narrative_agent_metadata": [
    {
      "agent_id": 1,
      "status": "success",
      "n_labels": 3
    },
    {
      "agent_id": 2,
      "status": "success",
      "n_labels": 3
    },
    {
      "agent_id": 3,
      "status": "success",
      "n_labels": 3
    }
  ],
  "subnarrative_agent_metadata": [],
  "narrative_fuzzy_matches": [
    {
      "original": "URW: Speculating war outcomes",
      "matched": "URW: Speculating war outcomes",
      "score": 100.0,
      "type": "exact"
    },
    {
      "original": "URW: Praise of Russia",
      "matched": "URW: Praise of Russia",
      "score": 100.0,
      "type": "exact"
    }
  ],
  "subnarrative_fuzzy_matches": [
    {
      "original": "URW: Speculating war outcomes: Russian army will lose all the occupied territories",
      "matched": "URW: Speculating war outcomes: Russian army will lose all the occupied territories",
      "score": 100.0,
      "type": "exact"
    },
    {
      "original": "URW: Speculating war outcomes: Other",
      "matched": "URW: Speculating war outcomes: Other",
      "score": 100.0,
      "type": "exact"
    },
    {
      "original": "URW: Praise of Russia: Praise of Russian military might",
      "matched": "URW: Praise of Russia: Praise of Russian military might",
      "score": 100.0,
      "type": "exact"
    },
    {
      "original": "URW: Praise of Russia: Russia is a guarantor of peace and prosperity",
      "matched": "URW: Praise of Russia: Russia is a guarantor of peace and prosperity",
      "score": 100.0,
      "type": "exact"
    }
  ]
}