{
  "file_id": "HI_140.txt",
  "narratives": [
    {
      "narrative_name": "CC: Amplifying Climate Fears",
      "evidence_quote": "रिपोर्ट आर्थिक विकास दो सिमा से जारी रहेगी",
      "reasoning": "वाक्य जलवायु परिवर्तन के प्रबाव से आर्थिक विकास दो सिमा से जारी रहेगी, जिससे विश्व शेली लोक विकास दो सिमा से जारी रहेगी है।"
    }
  ],
  "subnarratives": [
    {
      "subnarrative_name": "CC: Amplifying Climate Fears: Doomsday scenarios for humans",
      "evidence_quote": "सदी के मध्य तक वैश्विक सकल घरेलू उत्पाद में 17% की कमी",
      "reasoning": "यह अनुमान गहराई को रेखांकित करता है ग्लोबल वार्मिंग का प्रभाव विभिन्न क्षेत्रों पर और भविष्य की एक गंभीर तस्वीर पेश करता है, जो जलवायु परिवर्तन के कारण मानवता के लिए एक विनाशकारी परिदृश्य की ओर इशारा करता है।"
    },
    {
      "subnarrative_name": "CC: Amplifying Climate Fears: Amplifying existing fears of global warming",
      "evidence_quote": "जलवायु परिवर्तन से आर्थिक विकास धीमा हो जाएगा",
      "reasoning": "यह बयान मौजूदा जलवायु परिवर्तन के डर को बढ़ाता है और आर्थिक विकास पर इसके प्रभाव को रेखांकित करता है, जो लोगों को जलवायु परिवर्तन के प्रति और अधिक चिंतित बना सकता है।"
    },
    {
      "subnarrative_name": "CC: Amplifying Climate Fears: Earth will be uninhabitable soon",
      "evidence_quote": "सदी के अंत तक वैश्विक आय हानि 60% तक बढ़ सकती है",
      "reasoning": "यह अनुमान जलवायु परिवर्तन के कारण पृथ्वी के निकट भविष्य में असहज और संभावित रूप से निवासयोग्य न होने की एक गंभीर तस्वीर पेश करता है, जो लोगों को जलवायु परिवर्तन के प्रति अधिक चिंतित बना सकता है।"
    },
    {
      "subnarrative_name": "CC: Amplifying Climate Fears: Whatever we do it is already too late",
      "evidence_quote": "यदि वर्तमान उत्सर्जन दरें जारी रहती हैं और तापमान 4 डिग्री सेल्सियस से अधिक बढ़ने पर",
      "reasoning": "यह बयान यह सुझाव देता है कि यदि तुरंत कार्रवाई नहीं की जाती है, तो जलवायु परिवर्तन के प्रभावों को रोकने के लिए बहुत देर हो सकती है, जो लोगों को निराश और असहाय महसूस करा सकता है।"
    }
  ]
}