{
  "file_id": "HI_35.txt",
  "narratives": [
    {
      "narrative_name": "URW: Distrust towards Media",
      "evidence_quote": "रूसी प्रॉसिक्यूटर जनरल के कार्यालय ने देश की सेना को बदनाम करने का आरोप लगाते हुए 10 को जुलाई को रूस में वेबसाइट को ब्लॉक करने का आदेश जारी किया.",
      "reasoning": "यह उद्धरण रूसी सरकार द्वारा स्वतंत्र मीडिया पर प्रतिबंध लगाने के प्रयास को दर्शाता है, जो मीडिया की विश्वसनीयता पर संदेह पैदा करता है और इसकी स्वतंत्रता को कमजोर करता है।"
    },
    {
      "narrative_name": "URW: Discrediting the West, Diplomacy",
      "evidence_quote": "पिछले महीने रूसी सरकार ने अपने देश में 80 से अधिक पश्चिमी मीडिया आउटलेट्स पर प्रतिबंध लगा दिया था।",
      "reasoning": "यह उद्धरण रूसी सरकार द्वारा पश्चिमी मीडिया पर प्रतिबंध लगाने के प्रयास को दर्शाता है, जो पश्चिमी देशों की विश्वसनीयता और उनकी कूटनीतिक प्रयासों पर संदेह पैदा करता है।"
    }
  ],
  "subnarratives": [
    {
      "subnarrative_name": "URW: Distrust towards Media: Western media is an instrument of propaganda",
      "evidence_quote": "रूसी प्रॉसिक्यूटर जनरल के कार्यालय ने देश की सेना को बदनाम करने का आरोप लगाते हुए 10 को जुलाई को रूस में वेबसाइट को ब्लॉक करने का आदेश जारी किया",
      "reasoning": "इस उद्धरण में रूसी सरकार द्वारा पश्चिमी मीडिया पर प्रतिबंध लगाने का उल्लेख किया गया है, जो यह दर्शाता है कि रूसी सरकार पश्चिमी मीडिया को अपने देश की सेना को बदनाम करने का आरोप लगा रही है, जो कि पश्चिमी मीडिया को एक प्रोपगैंडा उपकरण के रूप में देखने की ओर इशारा करता है।"
    },
    {
      "subnarrative_name": "URW: Distrust towards Media: Other",
      "evidence_quote": "न्यूज वेबसाइट ने कहा है, ‘हमारा काम और भी मुश्किल होने जा रहा है. रूस में जो भी हमारे साथ किसी भी तरह से बातचीत करेगा, उस पर अब आपराधिक मुकदमा चलाया जाएगा.",
      "reasoning": "इस उद्धरण में रूसी सरकार द्वारा स्वतंत्र मीडिया पर नकेल कसने का उल्लेख किया गया है, जो यह दर्शाता है कि रूसी सरकार स्वतंत्र मीडिया को दबाने का प्रयास कर रही है, जो कि स्वतंत्र मीडिया के प्रति अविश्वास को बढ़ावा देने की ओर इशारा करता है।"
    },
    {
      "subnarrative_name": "URW: Discrediting the West, Diplomacy: The West is overreacting",
      "evidence_quote": "रूसी प्रॉसिक्यूटर जनरल के कार्यालय ने देश की सेना को बदनाम करने का आरोप लगाते हुए 10 को जुलाई को रूस में वेबसाइट को ब्लॉक करने का आदेश जारी किया",
      "reasoning": "इस उद्धरण में रूसी सरकार की कार्रवाइयों को स्वतंत्र मीडिया की स्वतंत्रता के प्रति खतरे के रूप में देखा जा रहा है, जो कि पश्चिमी देशों की प्रतिक्रिया को अतिरंजित करने के रूप में देखा जा सकता है।"
    },
    {
      "subnarrative_name": "URW: Discrediting the West, Diplomacy: Diplomacy does/will not work",
      "evidence_quote": "रूसी प्रॉसिक्यूटर जनरल के कार्यालय ने कहा है कि द मॉस्को टाइम्स पर प्रतिबंध आवश्यक था क्योंकि यह ऐसे मीडिया के साथ सहयोग करता था",
      "reasoning": "इस उद्धरण में रूसी सरकार की कार्रवाइयों को स्वतंत्र मीडिया की स्वतंत्रता के प्रति खतरे के रूप में देखा जा रहा है, जो कि राजनयिक प्रयासों की विफलता को दर्शाता है।"
    }
  ]
}